reqs_check/__init__.py
reqs_check/diff.py
reqs_check/duplicates.py
reqs_check/lint.py
reqs_check/main.py
reqs_check/utils.py
reqs_check/version.py
tests/__init__.py
tests/test_cli.py
tests/test_diff.py
tests/test_duplicates.py
tests/test_lint.py
tests/test_versions.py
reqs_check-0.3.0.dist-info/LICENSE
reqs_check-0.3.0.dist-info/METADATA
reqs_check-0.3.0.dist-info/WHEEL
reqs_check-0.3.0.dist-info/entry_points.txt
reqs_check-0.3.0.dist-info/top_level.txt
reqs_check-0.3.0.dist-info/RECORD
