Metadata-Version: 2.1
Name: reqs-check
Version: 0.3.0
Summary: A tool to check and compare dependencies(requirements.txt and so on) files for Python projects.
Home-page: https://github.com/bricefotzo/reqs-check
Author: Brice Fotzo
Author-email: bricef.tech@gmail.com
License: UNKNOWN
Platform: UNKNOWN
Classifier: Programming Language :: Python :: 3
Classifier: License :: OSI Approved :: MIT License
Classifier: Operating System :: OS Independent
Requires-Python: >=3.6
License-File: LICENSE
Requires-Dist: pandas
Requires-Dist: tabulate
Requires-Dist: termcolor
Requires-Dist: typer
